{
  "minecraft:recipes/decorations/crafting_table": {
    "criteria": {
      "unlock_right_away": "2025-06-14 11:56:12 +0200"
    },
    "done": true
  },
  "minecraft:adventure/adventuring_time": {
    "criteria": {
      "minecraft:taiga": "2025-06-14 11:57:05 +0200",
      "minecraft:beach": "2025-06-14 18:57:27 +0200",
      "minecraft:river": "2025-06-15 18:18:30 +0200",
      "minecraft:forest": "2025-06-14 11:57:37 +0200"
    },
    "done": false
  },
  "minecraft:nether/create_beacon": {
    "criteria": {
      "beacon": "2025-06-14 11:57:13 +0200"
    },
    "done": true
  },
  "minecraft:recipes/tools/recovery_compass": {
    "criteria": {
      "has_echo_shard": "2025-06-14 12:53:17 +0200"
    },
    "done": true
  },
  "minecraft:recipes/building_blocks/nether_bricks": {
    "criteria": {
      "has_nether_brick": "2025-06-14 12:53:24 +0200"
    },
    "done": true
  },
  "minecraft:recipes/misc/netherite_scrap_from_blasting": {
    "criteria": {
      "has_ancient_debris": "2025-06-14 12:53:31 +0200"
    },
    "done": true
  },
  "minecraft:recipes/misc/netherite_scrap": {
    "criteria": {
      "has_ancient_debris": "2025-06-14 12:53:31 +0200"
    },
    "done": true
  },
  "minecraft:nether/obtain_ancient_debris": {
    "criteria": {
      "ancient_debris": "2025-06-14 12:53:31 +0200"
    },
    "done": true
  },
  "minecraft:recipes/building_blocks/blackstone_stairs": {
    "criteria": {
      "has_blackstone": "2025-06-14 12:53:49 +0200"
    },
    "done": true
  },
  "minecraft:recipes/building_blocks/blackstone_slab_from_blackstone_stonecutting": {
    "criteria": {
      "has_blackstone": "2025-06-14 12:53:49 +0200"
    },
    "done": true
  },
  "minecraft:recipes/decorations/polished_blackstone_brick_wall_from_blackstone_stonecutting": {
    "criteria": {
      "has_blackstone": "2025-06-14 12:53:49 +0200"
    },
    "done": true
  },
  "minecraft:recipes/building_blocks/polished_blackstone_slab_from_blackstone_stonecutting": {
    "criteria": {
      "has_blackstone": "2025-06-14 12:53:49 +0200"
    },
    "done": true
  },
  "minecraft:recipes/combat/stone_sword": {
    "criteria": {
      "has_cobblestone": "2025-06-14 12:53:49 +0200"
    },
    "done": true
  },
  "minecraft:recipes/tools/stone_pickaxe": {
    "criteria": {
      "has_cobblestone": "2025-06-14 12:53:49 +0200"
    },
    "done": true
  },
  "minecraft:recipes/tools/stone_axe": {
    "criteria": {
      "has_cobblestone": "2025-06-14 12:53:49 +0200"
    },
    "done": true
  },
  "minecraft:story/mine_stone": {
    "criteria": {
      "get_stone": "2025-06-14 12:53:49 +0200"
    },
    "done": true
  },
  "minecraft:recipes/decorations/furnace": {
    "criteria": {
      "has_cobblestone": "2025-06-14 12:53:49 +0200"
    },
    "done": true
  },
  "minecraft:recipes/building_blocks/polished_blackstone": {
    "criteria": {
      "has_blackstone": "2025-06-14 12:53:49 +0200"
    },
    "done": true
  },
  "minecraft:recipes/decorations/blackstone_wall": {
    "criteria": {
      "has_blackstone": "2025-06-14 12:53:49 +0200"
    },
    "done": true
  },
  "minecraft:recipes/building_blocks/blackstone_slab": {
    "criteria": {
      "has_blackstone": "2025-06-14 12:53:49 +0200"
    },
    "done": true
  },
  "minecraft:recipes/building_blocks/polished_blackstone_brick_slab_from_blackstone_stonecutting": {
    "criteria": {
      "has_blackstone": "2025-06-14 12:53:49 +0200"
    },
    "done": true
  },
  "minecraft:recipes/building_blocks/polished_blackstone_from_blackstone_stonecutting": {
    "criteria": {
      "has_blackstone": "2025-06-14 12:53:49 +0200"
    },
    "done": true
  },
  "minecraft:recipes/building_blocks/polished_blackstone_brick_stairs_from_blackstone_stonecutting": {
    "criteria": {
      "has_blackstone": "2025-06-14 12:53:49 +0200"
    },
    "done": true
  },
  "minecraft:recipes/building_blocks/polished_blackstone_bricks_from_blackstone_stonecutting": {
    "criteria": {
      "has_blackstone": "2025-06-14 12:53:49 +0200"
    },
    "done": true
  },
  "minecraft:recipes/decorations/blackstone_wall_from_blackstone_stonecutting": {
    "criteria": {
      "has_blackstone": "2025-06-14 12:53:49 +0200"
    },
    "done": true
  },
  "minecraft:recipes/building_blocks/polished_blackstone_stairs_from_blackstone_stonecutting": {
    "criteria": {
      "has_blackstone": "2025-06-14 12:53:49 +0200"
    },
    "done": true
  },
  "minecraft:recipes/tools/stone_hoe": {
    "criteria": {
      "has_cobblestone": "2025-06-14 12:53:49 +0200"
    },
    "done": true
  },
  "minecraft:recipes/tools/stone_shovel": {
    "criteria": {
      "has_cobblestone": "2025-06-14 12:53:49 +0200"
    },
    "done": true
  },
  "minecraft:recipes/decorations/polished_blackstone_wall_from_blackstone_stonecutting": {
    "criteria": {
      "has_blackstone": "2025-06-14 12:53:49 +0200"
    },
    "done": true
  },
  "minecraft:recipes/building_blocks/chiseled_polished_blackstone_from_blackstone_stonecutting": {
    "criteria": {
      "has_blackstone": "2025-06-14 12:53:49 +0200"
    },
    "done": true
  },
  "minecraft:recipes/building_blocks/blackstone_stairs_from_blackstone_stonecutting": {
    "criteria": {
      "has_blackstone": "2025-06-14 12:53:49 +0200"
    },
    "done": true
  },
  "minecraft:recipes/building_blocks/smooth_basalt": {
    "criteria": {
      "has_basalt": "2025-06-14 12:53:54 +0200"
    },
    "done": true
  },
  "minecraft:recipes/building_blocks/polished_basalt_from_basalt_stonecutting": {
    "criteria": {
      "has_basalt": "2025-06-14 12:53:54 +0200"
    },
    "done": true
  },
  "minecraft:recipes/building_blocks/polished_basalt": {
    "criteria": {
      "has_basalt": "2025-06-14 12:53:54 +0200"
    },
    "done": true
  },
  "minecraft:recipes/decorations/soul_campfire": {
    "criteria": {
      "has_soul_sand": "2025-06-14 12:54:22 +0200"
    },
    "done": true
  },
  "minecraft:recipes/decorations/soul_torch": {
    "criteria": {
      "has_soul_sand": "2025-06-14 12:54:22 +0200"
    },
    "done": true
  },
  "utility:the_liminalykey": {
    "criteria": {
      "the_liminalykey_0": "2025-06-14 14:22:30 +0200"
    },
    "done": true
  },
  "utility:a_powerfullshard": {
    "criteria": {
      "a_powerfullshard_0": "2025-06-14 14:22:30 +0200"
    },
    "done": true
  },
  "utility:the_key": {
    "criteria": {
      "the_key_0": "2025-06-14 14:22:37 +0200"
    },
    "done": true
  },
  "utility:over_worldkey": {
    "criteria": {
      "over_worldkey_0": "2025-06-14 14:22:39 +0200"
    },
    "done": true
  },
  "utility:thelimbo": {
    "criteria": {
      "thelimbo_0": "2025-06-14 14:22:39 +0200"
    },
    "done": true
  },
  "utility:the_overworldkey": {
    "criteria": {
      "the_overworldkey_0": "2025-06-14 14:22:39 +0200"
    },
    "done": true
  },
  "utility:poweressece": {
    "criteria": {
      "poweressece_0": "2025-06-14 14:23:45 +0200"
    },
    "done": true
  },
  "utility:theflatworldkey": {
    "criteria": {
      "theflatworldkey_0": "2025-06-14 14:24:12 +0200"
    },
    "done": true
  },
  "utility:theflatkey": {
    "criteria": {
      "theflatkey_0": "2025-06-14 14:24:12 +0200"
    },
    "done": true
  },
  "utility:the_netherkey": {
    "criteria": {
      "the_netherkey_0": "2025-06-14 14:24:17 +0200"
    },
    "done": true
  },
  "utility:thenetherkey": {
    "criteria": {
      "thenetherkey_0": "2025-06-14 14:24:17 +0200"
    },
    "done": true
  },
  "utility:theendkey": {
    "criteria": {
      "theendkey_0": "2025-06-14 14:24:22 +0200"
    },
    "done": true
  },
  "utility:the_endkey": {
    "criteria": {
      "the_endkey_0": "2025-06-14 14:24:22 +0200"
    },
    "done": true
  },
  "minecraft:recipes/decorations/chest": {
    "criteria": {
      "has_lots_of_items": "2025-06-14 18:56:34 +0200"
    },
    "done": true
  },
  "minecraft:adventure/root": {
    "criteria": {
      "killed_something": "2025-06-14 18:57:28 +0200"
    },
    "done": true
  },
  "minecraft:recipes/food/cooked_beef_from_smoking": {
    "criteria": {
      "has_beef": "2025-06-14 18:57:48 +0200"
    },
    "done": true
  },
  "minecraft:recipes/food/cooked_beef": {
    "criteria": {
      "has_beef": "2025-06-14 18:57:48 +0200"
    },
    "done": true
  },
  "minecraft:recipes/food/cooked_beef_from_campfire_cooking": {
    "criteria": {
      "has_beef": "2025-06-14 18:57:48 +0200"
    },
    "done": true
  },
  "minecraft:adventure/kill_all_mobs": {
    "criteria": {
      "minecraft:skeleton": "2025-06-15 18:12:30 +0200",
      "minecraft:spider": "2025-06-15 18:12:18 +0200",
      "minecraft:zombified_piglin": "2025-06-14 18:57:55 +0200",
      "minecraft:zombie": "2025-06-14 18:59:24 +0200"
    },
    "done": false
  },
  "minecraft:adventure/kill_a_mob": {
    "criteria": {
      "minecraft:zombified_piglin": "2025-06-14 18:57:55 +0200"
    },
    "done": true
  },
  "minecraft:recipes/decorations/white_banner": {
    "criteria": {
      "has_white_wool": "2025-06-14 18:58:04 +0200"
    },
    "done": true
  },
  "minecraft:recipes/decorations/painting": {
    "criteria": {
      "has_wool": "2025-06-14 18:58:04 +0200"
    },
    "done": true
  },
  "minecraft:recipes/decorations/white_bed": {
    "criteria": {
      "has_white_wool": "2025-06-14 18:58:04 +0200"
    },
    "done": true
  },
  "minecraft:recipes/decorations/white_carpet": {
    "criteria": {
      "has_white_wool": "2025-06-14 18:58:04 +0200"
    },
    "done": true
  },
  "minecraft:nether/netherite_armor": {
    "criteria": {
      "netherite_armor": "2025-06-14 19:13:58 +0200"
    },
    "done": true
  },
  "minecraft:recipes/misc/leather": {
    "criteria": {
      "has_rabbit_hide": "2025-06-15 18:12:01 +0200"
    },
    "done": true
  },
  "minecraft:recipes/misc/bone_meal": {
    "criteria": {
      "has_bone": "2025-06-15 18:12:48 +0200"
    },
    "done": true
  },
  "minecraft:recipes/transportation/mangrove_boat": {
    "criteria": {
      "in_water": "2025-06-15 18:17:25 +0200"
    },
    "done": true
  },
  "minecraft:recipes/transportation/acacia_boat": {
    "criteria": {
      "in_water": "2025-06-15 18:17:25 +0200"
    },
    "done": true
  },
  "minecraft:recipes/transportation/cherry_boat": {
    "criteria": {
      "in_water": "2025-06-15 18:17:25 +0200"
    },
    "done": true
  },
  "minecraft:recipes/transportation/bamboo_raft": {
    "criteria": {
      "in_water": "2025-06-15 18:17:25 +0200"
    },
    "done": true
  },
  "minecraft:recipes/transportation/spruce_boat": {
    "criteria": {
      "in_water": "2025-06-15 18:17:25 +0200"
    },
    "done": true
  },
  "minecraft:recipes/transportation/birch_boat": {
    "criteria": {
      "in_water": "2025-06-15 18:17:25 +0200"
    },
    "done": true
  },
  "minecraft:recipes/transportation/oak_boat": {
    "criteria": {
      "in_water": "2025-06-15 18:17:25 +0200"
    },
    "done": true
  },
  "minecraft:recipes/transportation/jungle_boat": {
    "criteria": {
      "in_water": "2025-06-15 18:17:25 +0200"
    },
    "done": true
  },
  "minecraft:recipes/transportation/dark_oak_boat": {
    "criteria": {
      "in_water": "2025-06-15 18:17:25 +0200"
    },
    "done": true
  },
  "minecraft:story/root": {
    "criteria": {
      "crafting_table": "2025-06-16 13:41:03 +0200"
    },
    "done": true
  },
  "minecraft:recipes/combat/iron_sword": {
    "criteria": {
      "has_iron_ingot": "2025-06-16 13:41:05 +0200"
    },
    "done": true
  },
  "minecraft:recipes/tools/iron_pickaxe": {
    "criteria": {
      "has_iron_ingot": "2025-06-16 13:41:05 +0200"
    },
    "done": true
  },
  "minecraft:recipes/combat/iron_leggings": {
    "criteria": {
      "has_iron_ingot": "2025-06-16 13:41:05 +0200"
    },
    "done": true
  },
  "minecraft:recipes/combat/shield": {
    "criteria": {
      "has_iron_ingot": "2025-06-16 13:41:05 +0200"
    },
    "done": true
  },
  "minecraft:recipes/redstone/hopper": {
    "criteria": {
      "has_iron_ingot": "2025-06-16 13:41:05 +0200"
    },
    "done": true
  },
  "minecraft:recipes/decorations/iron_bars": {
    "criteria": {
      "has_iron_ingot": "2025-06-16 13:41:05 +0200"
    },
    "done": true
  },
  "minecraft:recipes/combat/iron_boots": {
    "criteria": {
      "has_iron_ingot": "2025-06-16 13:41:05 +0200"
    },
    "done": true
  },
  "minecraft:recipes/combat/iron_chestplate": {
    "criteria": {
      "has_iron_ingot": "2025-06-16 13:41:05 +0200"
    },
    "done": true
  },
  "minecraft:recipes/decorations/lantern": {
    "criteria": {
      "has_iron_ingot": "2025-06-16 13:41:05 +0200"
    },
    "done": true
  },
  "minecraft:recipes/misc/iron_nugget": {
    "criteria": {
      "has_iron_ingot": "2025-06-16 13:41:05 +0200"
    },
    "done": true
  },
  "minecraft:recipes/misc/bucket": {
    "criteria": {
      "has_iron_ingot": "2025-06-16 13:41:05 +0200"
    },
    "done": true
  },
  "minecraft:recipes/combat/iron_helmet": {
    "criteria": {
      "has_iron_ingot": "2025-06-16 13:41:05 +0200"
    },
    "done": true
  },
  "minecraft:recipes/transportation/minecart": {
    "criteria": {
      "has_iron_ingot": "2025-06-16 13:41:05 +0200"
    },
    "done": true
  },
  "minecraft:recipes/tools/iron_hoe": {
    "criteria": {
      "has_iron_ingot": "2025-06-16 13:41:05 +0200"
    },
    "done": true
  },
  "minecraft:recipes/tools/iron_shovel": {
    "criteria": {
      "has_iron_ingot": "2025-06-16 13:41:05 +0200"
    },
    "done": true
  },
  "minecraft:story/smelt_iron": {
    "criteria": {
      "iron": "2025-06-16 13:41:05 +0200"
    },
    "done": true
  },
  "minecraft:recipes/tools/shears": {
    "criteria": {
      "has_iron_ingot": "2025-06-16 13:41:05 +0200"
    },
    "done": true
  },
  "minecraft:recipes/redstone/iron_trapdoor": {
    "criteria": {
      "has_iron_ingot": "2025-06-16 13:41:05 +0200"
    },
    "done": true
  },
  "minecraft:recipes/decorations/chain": {
    "criteria": {
      "has_iron_ingot": "2025-06-16 13:41:05 +0200"
    },
    "done": true
  },
  "minecraft:recipes/building_blocks/iron_block": {
    "criteria": {
      "has_iron_ingot": "2025-06-16 13:41:05 +0200"
    },
    "done": true
  },
  "minecraft:recipes/tools/iron_axe": {
    "criteria": {
      "has_iron_ingot": "2025-06-16 13:41:05 +0200"
    },
    "done": true
  },
  "minecraft:recipes/combat/crossbow": {
    "criteria": {
      "has_iron_ingot": "2025-06-16 13:41:05 +0200"
    },
    "done": true
  },
  "minecraft:recipes/decorations/smithing_table": {
    "criteria": {
      "has_iron_ingot": "2025-06-16 13:41:05 +0200"
    },
    "done": true
  },
  "minecraft:recipes/redstone/iron_door": {
    "criteria": {
      "has_iron_ingot": "2025-06-16 13:41:05 +0200"
    },
    "done": true
  },
  "minecraft:recipes/redstone/heavy_weighted_pressure_plate": {
    "criteria": {
      "has_iron_ingot": "2025-06-16 13:41:05 +0200"
    },
    "done": true
  },
  "minecraft:recipes/building_blocks/netherite_block": {
    "criteria": {
      "has_netherite_ingot": "2025-06-16 13:41:06 +0200"
    },
    "done": true
  },
  "minecraft:recipes/combat/netherite_boots_smithing": {
    "criteria": {
      "has_netherite_ingot": "2025-06-16 13:41:06 +0200"
    },
    "done": true
  },
  "minecraft:recipes/tools/netherite_shovel_smithing": {
    "criteria": {
      "has_netherite_ingot": "2025-06-16 13:41:06 +0200"
    },
    "done": true
  },
  "minecraft:recipes/combat/netherite_chestplate_smithing": {
    "criteria": {
      "has_netherite_ingot": "2025-06-16 13:41:06 +0200"
    },
    "done": true
  },
  "minecraft:recipes/combat/netherite_sword_smithing": {
    "criteria": {
      "has_netherite_ingot": "2025-06-16 13:41:06 +0200"
    },
    "done": true
  },
  "minecraft:recipes/combat/netherite_leggings_smithing": {
    "criteria": {
      "has_netherite_ingot": "2025-06-16 13:41:06 +0200"
    },
    "done": true
  },
  "minecraft:recipes/tools/netherite_axe_smithing": {
    "criteria": {
      "has_netherite_ingot": "2025-06-16 13:41:06 +0200"
    },
    "done": true
  },
  "minecraft:recipes/tools/netherite_hoe_smithing": {
    "criteria": {
      "has_netherite_ingot": "2025-06-16 13:41:06 +0200"
    },
    "done": true
  },
  "minecraft:recipes/tools/netherite_pickaxe_smithing": {
    "criteria": {
      "has_netherite_ingot": "2025-06-16 13:41:06 +0200"
    },
    "done": true
  },
  "minecraft:recipes/decorations/lodestone": {
    "criteria": {
      "has_netherite_ingot": "2025-06-16 13:41:06 +0200"
    },
    "done": true
  },
  "minecraft:recipes/combat/netherite_helmet_smithing": {
    "criteria": {
      "has_netherite_ingot": "2025-06-16 13:41:06 +0200"
    },
    "done": true
  },
  "minecraft:recipes/misc/iron_ingot_from_iron_block": {
    "criteria": {
      "has_iron_block": "2025-06-16 13:41:23 +0200"
    },
    "done": true
  },
  "minecraft:recipes/decorations/anvil": {
    "criteria": {
      "has_iron_block": "2025-06-16 13:41:23 +0200"
    },
    "done": true
  },
  "utility:tacticalsuit": {
    "criteria": {
      "tacticalsuit_0": "2025-06-16 19:41:12 +0200",
      "tacticalsuit_2": "2025-06-16 19:41:25 +0200",
      "tacticalsuit_1": "2025-06-16 19:41:24 +0200",
      "tacticalsuit_3": "2025-06-16 19:41:26 +0200"
    },
    "done": true
  },
  "utility:the_empyt_key": {
    "criteria": {
      "the_empyt_key_0": "2025-06-16 19:41:46 +0200"
    },
    "done": true
  },
  "minecraft:recipes/food/cake": {
    "criteria": {
      "has_egg": "2025-06-16 19:45:17 +0200"
    },
    "done": true
  },
  "minecraft:recipes/misc/white_dye_from_lily_of_the_valley": {
    "criteria": {
      "has_lily_of_the_valley": "2025-06-16 19:49:06 +0200"
    },
    "done": true
  },
  "minecraft:recipes/misc/charcoal": {
    "criteria": {
      "has_log": "2025-06-16 19:49:06 +0200"
    },
    "done": true
  },
  "minecraft:recipes/building_blocks/oak_planks": {
    "criteria": {
      "has_logs": "2025-06-16 19:49:06 +0200"
    },
    "done": true
  },
  "minecraft:husbandry/balanced_diet": {
    "criteria": {
      "bread": "2025-06-16 19:45:11 +0200"
    },
    "done": false
  },
  "minecraft:husbandry/root": {
    "criteria": {
      "consumed_item": "2025-06-16 19:44:46 +0200"
    },
    "done": true
  },
  "minecraft:recipes/building_blocks/oak_wood": {
    "criteria": {
      "has_log": "2025-06-16 19:49:06 +0200"
    },
    "done": true
  },
  "DataVersion": 3465
}